DiveIntoPython3Zhongwenban/README.md
DiveIntoPython3Zhongwenban/__init__.py
DiveIntoPython3Zhongwenban/__main__.py
DiveIntoPython3Zhongwenban/file.epub
DiveIntoPython3Zhongwenban/index.html
DiveIntoPython3Zhongwenban/css/__init__.py
DiveIntoPython3Zhongwenban/css/annotations.css
DiveIntoPython3Zhongwenban/css/main.css
DiveIntoPython3Zhongwenban/css/normalize.css
DiveIntoPython3Zhongwenban/css/popup.css
DiveIntoPython3Zhongwenban/font/__init__.py
DiveIntoPython3Zhongwenban/font/fontello.eot
DiveIntoPython3Zhongwenban/font/fontello.svg
DiveIntoPython3Zhongwenban/font/fontello.ttf
DiveIntoPython3Zhongwenban/font/fontello.woff
DiveIntoPython3Zhongwenban/img/__init__.py
DiveIntoPython3Zhongwenban/img/annotator-glyph-sprite.png
DiveIntoPython3Zhongwenban/img/annotator-icon-sprite.png
DiveIntoPython3Zhongwenban/img/apple-touch-icon.png
DiveIntoPython3Zhongwenban/img/cancelfullscreen.png
DiveIntoPython3Zhongwenban/img/close.png
DiveIntoPython3Zhongwenban/img/fullscreen.png
DiveIntoPython3Zhongwenban/img/loader.gif
DiveIntoPython3Zhongwenban/img/menu-icon.png
DiveIntoPython3Zhongwenban/img/save.png
DiveIntoPython3Zhongwenban/img/saved.png
DiveIntoPython3Zhongwenban/img/settings-s.png
DiveIntoPython3Zhongwenban/img/settings.png
DiveIntoPython3Zhongwenban/img/star.png
DiveIntoPython3Zhongwenban/js/__init__.py
DiveIntoPython3Zhongwenban/js/epub.js
DiveIntoPython3Zhongwenban/js/epub.min.js
DiveIntoPython3Zhongwenban/js/epub.min.map
DiveIntoPython3Zhongwenban/js/hooks.min.js
DiveIntoPython3Zhongwenban/js/hooks.min.map
DiveIntoPython3Zhongwenban/js/reader.js
DiveIntoPython3Zhongwenban/js/reader.js.map
DiveIntoPython3Zhongwenban/js/reader.min.js
DiveIntoPython3Zhongwenban/js/reader.min.map
DiveIntoPython3Zhongwenban/js/hooks/__init__.py
DiveIntoPython3Zhongwenban/js/hooks/extensions/__init__.py
DiveIntoPython3Zhongwenban/js/hooks/extensions/highlight.js
DiveIntoPython3Zhongwenban/js/libs/__init__.py
DiveIntoPython3Zhongwenban/js/libs/jquery.min.js
dive_into_python3_zhongwenban-2024.3.1.0.dist-info/METADATA
dive_into_python3_zhongwenban-2024.3.1.0.dist-info/WHEEL
dive_into_python3_zhongwenban-2024.3.1.0.dist-info/entry_points.txt
dive_into_python3_zhongwenban-2024.3.1.0.dist-info/top_level.txt
dive_into_python3_zhongwenban-2024.3.1.0.dist-info/RECORD
